arqonhpo/__init__.py
arqonhpo/__main__.py
arqonhpo/_internal.cpython-312-powerpc64le-linux-gnu.so
arqonhpo/cli.py
arqonhpo-0.3.3.dist-info/METADATA
arqonhpo-0.3.3.dist-info/WHEEL
arqonhpo-0.3.3.dist-info/entry_points.txt
arqonhpo-0.3.3.dist-info/RECORD
