Metadata-Version: 2.4
Name: arqonhpo
Version: 0.3.3
Classifier: Programming Language :: Rust
Classifier: Programming Language :: Python :: Implementation :: CPython
Classifier: Programming Language :: Python :: Implementation :: PyPy
Summary: High-performance hyperparameter optimization engine.
Requires-Python: >=3.10
